MANIFEST.in
README.rst
setup.cfg
setup.py
docs/HISTORY.txt
src/plone/__init__.py
src/plone.multilingual.egg-info/PKG-INFO
src/plone.multilingual.egg-info/SOURCES.txt
src/plone.multilingual.egg-info/dependency_links.txt
src/plone.multilingual.egg-info/entry_points.txt
src/plone.multilingual.egg-info/namespace_packages.txt
src/plone.multilingual.egg-info/not-zip-safe
src/plone.multilingual.egg-info/requires.txt
src/plone.multilingual.egg-info/top_level.txt
src/plone/multilingual/__init__.py
src/plone/multilingual/adapter.py
src/plone/multilingual/canonical.py
src/plone/multilingual/configure.zcml
src/plone/multilingual/events.py
src/plone/multilingual/factory.py
src/plone/multilingual/handlers.py
src/plone/multilingual/indexer.py
src/plone/multilingual/interfaces.py
src/plone/multilingual/manager.py
src/plone/multilingual/profile.zcml
src/plone/multilingual/storage.py
src/plone/multilingual/subscriber.py
src/plone/multilingual/testing.py
src/plone/multilingual/testing.zcml
src/plone/multilingual/profiles/default/componentregistry.xml
src/plone/multilingual/profiles/default/metadata.xml
src/plone/multilingual/profiles/default/plone.multilingua-reindex.txt
src/plone/multilingual/profiles/default/plone.multilingual.default.txt
src/plone/multilingual/profiles/testing/catalog.xml
src/plone/multilingual/profiles/testing/metadata.xml
src/plone/multilingual/profiles/uninstall/componentregistry.xml
src/plone/multilingual/profiles/uninstall/plone.multilingual.uninstall.txt
src/plone/multilingual/tests/__init__.py
src/plone/multilingual/tests/configure.zcml
src/plone/multilingual/tests/test_doctests.py
src/plone/multilingual/tests/test_subscribers.py
src/plone/multilingual/upgrades/__init__.py
src/plone/multilingual/upgrades/configure.zcml
src/plone/multilingual/upgrades/to02.py
src/plone/multilingual/upgrades/to03.py