Metadata-Version: 1.1
Name: plone.multilingual
Version: 1.1
Summary: Multilingual extensions core package
Home-page: https://github.com/plone/plone.multilingual/
Author: Ramon Navarro Bosch
Author-email: ramon@.nb@gmail.com
License: GPL
Platform: UNKNOWN
Classifier: Framework :: Plone
Classifier: Programming Language :: Python
